knygynas/Biblioteka.py
knygynas/knyga.py
knygynas/Mainas.py
knygynas/skaitytojas.py
knygynas-0.1.0.dist-info/METADATA
knygynas-0.1.0.dist-info/WHEEL
knygynas-0.1.0.dist-info/RECORD
