Metadata-Version: 2.1
Name: knygynas
Version: 0.1.0
Summary: 
Author: Robertas1993
Author-email: Entrepreneur0508@gmail.com
Requires-Python: >=3.12,<4.0
Classifier: Programming Language :: Python :: 3
Classifier: Programming Language :: Python :: 3.12
